aws_cdk/cloudformation_include/__init__.py
aws_cdk/cloudformation_include/py.typed
aws_cdk/cloudformation_include/_jsii/__init__.py
aws_cdk/cloudformation_include/_jsii/cloudformation-include@1.204.0.jsii.tgz
aws_cdk.cloudformation_include-1.204.0.dist-info/LICENSE
aws_cdk.cloudformation_include-1.204.0.dist-info/METADATA
aws_cdk.cloudformation_include-1.204.0.dist-info/NOTICE
aws_cdk.cloudformation_include-1.204.0.dist-info/WHEEL
aws_cdk.cloudformation_include-1.204.0.dist-info/top_level.txt
aws_cdk.cloudformation_include-1.204.0.dist-info/RECORD
