Metadata-Version: 2.1
Name: aws-cdk.cloudformation-include
Version: 1.204.0
Summary: A package that facilitates working with existing CloudFormation templates in the CDK
Home-page: https://github.com/aws/aws-cdk
Author: Amazon Web Services
License: Apache-2.0
Project-URL: Source, https://github.com/aws/aws-cdk.git
Classifier: Intended Audience :: Developers
Classifier: Operating System :: OS Independent
Classifier: Programming Language :: JavaScript
Classifier: Programming Language :: Python :: 3 :: Only
Classifier: Programming Language :: Python :: 3.7
Classifier: Programming Language :: Python :: 3.8
Classifier: Programming Language :: Python :: 3.9
Classifier: Programming Language :: Python :: 3.10
Classifier: Programming Language :: Python :: 3.11
Classifier: Typing :: Typed
Classifier: Development Status :: 7 - Inactive
Classifier: License :: OSI Approved
Classifier: Framework :: AWS CDK
Classifier: Framework :: AWS CDK :: 1
Requires-Python: ~=3.7
License-File: LICENSE
License-File: NOTICE
Requires-Dist: aws-cdk.alexa-ask (==1.204.0)
Requires-Dist: aws-cdk.aws-accessanalyzer (==1.204.0)
Requires-Dist: aws-cdk.aws-acmpca (==1.204.0)
Requires-Dist: aws-cdk.aws-amazonmq (==1.204.0)
Requires-Dist: aws-cdk.aws-amplify (==1.204.0)
Requires-Dist: aws-cdk.aws-amplifyuibuilder (==1.204.0)
Requires-Dist: aws-cdk.aws-apigateway (==1.204.0)
Requires-Dist: aws-cdk.aws-apigatewayv2 (==1.204.0)
Requires-Dist: aws-cdk.aws-appconfig (==1.204.0)
Requires-Dist: aws-cdk.aws-appflow (==1.204.0)
Requires-Dist: aws-cdk.aws-appintegrations (==1.204.0)
Requires-Dist: aws-cdk.aws-applicationautoscaling (==1.204.0)
Requires-Dist: aws-cdk.aws-applicationinsights (==1.204.0)
Requires-Dist: aws-cdk.aws-appmesh (==1.204.0)
Requires-Dist: aws-cdk.aws-apprunner (==1.204.0)
Requires-Dist: aws-cdk.aws-appstream (==1.204.0)
Requires-Dist: aws-cdk.aws-appsync (==1.204.0)
Requires-Dist: aws-cdk.aws-aps (==1.204.0)
Requires-Dist: aws-cdk.aws-athena (==1.204.0)
Requires-Dist: aws-cdk.aws-auditmanager (==1.204.0)
Requires-Dist: aws-cdk.aws-autoscaling (==1.204.0)
Requires-Dist: aws-cdk.aws-autoscalingplans (==1.204.0)
Requires-Dist: aws-cdk.aws-backup (==1.204.0)
Requires-Dist: aws-cdk.aws-backupgateway (==1.204.0)
Requires-Dist: aws-cdk.aws-batch (==1.204.0)
Requires-Dist: aws-cdk.aws-billingconductor (==1.204.0)
Requires-Dist: aws-cdk.aws-budgets (==1.204.0)
Requires-Dist: aws-cdk.aws-cassandra (==1.204.0)
Requires-Dist: aws-cdk.aws-ce (==1.204.0)
Requires-Dist: aws-cdk.aws-certificatemanager (==1.204.0)
Requires-Dist: aws-cdk.aws-chatbot (==1.204.0)
Requires-Dist: aws-cdk.aws-cloud9 (==1.204.0)
Requires-Dist: aws-cdk.aws-cloudfront (==1.204.0)
Requires-Dist: aws-cdk.aws-cloudtrail (==1.204.0)
Requires-Dist: aws-cdk.aws-cloudwatch (==1.204.0)
Requires-Dist: aws-cdk.aws-codeartifact (==1.204.0)
Requires-Dist: aws-cdk.aws-codebuild (==1.204.0)
Requires-Dist: aws-cdk.aws-codecommit (==1.204.0)
Requires-Dist: aws-cdk.aws-codedeploy (==1.204.0)
Requires-Dist: aws-cdk.aws-codeguruprofiler (==1.204.0)
Requires-Dist: aws-cdk.aws-codegurureviewer (==1.204.0)
Requires-Dist: aws-cdk.aws-codepipeline (==1.204.0)
Requires-Dist: aws-cdk.aws-codestar (==1.204.0)
Requires-Dist: aws-cdk.aws-codestarconnections (==1.204.0)
Requires-Dist: aws-cdk.aws-codestarnotifications (==1.204.0)
Requires-Dist: aws-cdk.aws-cognito (==1.204.0)
Requires-Dist: aws-cdk.aws-comprehend (==1.204.0)
Requires-Dist: aws-cdk.aws-config (==1.204.0)
Requires-Dist: aws-cdk.aws-connect (==1.204.0)
Requires-Dist: aws-cdk.aws-connectcampaigns (==1.204.0)
Requires-Dist: aws-cdk.aws-controltower (==1.204.0)
Requires-Dist: aws-cdk.aws-cur (==1.204.0)
Requires-Dist: aws-cdk.aws-customerprofiles (==1.204.0)
Requires-Dist: aws-cdk.aws-databrew (==1.204.0)
Requires-Dist: aws-cdk.aws-datapipeline (==1.204.0)
Requires-Dist: aws-cdk.aws-datasync (==1.204.0)
Requires-Dist: aws-cdk.aws-dax (==1.204.0)
Requires-Dist: aws-cdk.aws-detective (==1.204.0)
Requires-Dist: aws-cdk.aws-devopsguru (==1.204.0)
Requires-Dist: aws-cdk.aws-directoryservice (==1.204.0)
Requires-Dist: aws-cdk.aws-dlm (==1.204.0)
Requires-Dist: aws-cdk.aws-dms (==1.204.0)
Requires-Dist: aws-cdk.aws-docdb (==1.204.0)
Requires-Dist: aws-cdk.aws-docdbelastic (==1.204.0)
Requires-Dist: aws-cdk.aws-dynamodb (==1.204.0)
Requires-Dist: aws-cdk.aws-ec2 (==1.204.0)
Requires-Dist: aws-cdk.aws-ecr (==1.204.0)
Requires-Dist: aws-cdk.aws-ecs (==1.204.0)
Requires-Dist: aws-cdk.aws-efs (==1.204.0)
Requires-Dist: aws-cdk.aws-eks (==1.204.0)
Requires-Dist: aws-cdk.aws-elasticache (==1.204.0)
Requires-Dist: aws-cdk.aws-elasticbeanstalk (==1.204.0)
Requires-Dist: aws-cdk.aws-elasticloadbalancing (==1.204.0)
Requires-Dist: aws-cdk.aws-elasticloadbalancingv2 (==1.204.0)
Requires-Dist: aws-cdk.aws-elasticsearch (==1.204.0)
Requires-Dist: aws-cdk.aws-emr (==1.204.0)
Requires-Dist: aws-cdk.aws-emrcontainers (==1.204.0)
Requires-Dist: aws-cdk.aws-emrserverless (==1.204.0)
Requires-Dist: aws-cdk.aws-events (==1.204.0)
Requires-Dist: aws-cdk.aws-eventschemas (==1.204.0)
Requires-Dist: aws-cdk.aws-evidently (==1.204.0)
Requires-Dist: aws-cdk.aws-finspace (==1.204.0)
Requires-Dist: aws-cdk.aws-fis (==1.204.0)
Requires-Dist: aws-cdk.aws-fms (==1.204.0)
Requires-Dist: aws-cdk.aws-forecast (==1.204.0)
Requires-Dist: aws-cdk.aws-frauddetector (==1.204.0)
Requires-Dist: aws-cdk.aws-fsx (==1.204.0)
Requires-Dist: aws-cdk.aws-gamelift (==1.204.0)
Requires-Dist: aws-cdk.aws-globalaccelerator (==1.204.0)
Requires-Dist: aws-cdk.aws-glue (==1.204.0)
Requires-Dist: aws-cdk.aws-grafana (==1.204.0)
Requires-Dist: aws-cdk.aws-greengrass (==1.204.0)
Requires-Dist: aws-cdk.aws-greengrassv2 (==1.204.0)
Requires-Dist: aws-cdk.aws-groundstation (==1.204.0)
Requires-Dist: aws-cdk.aws-guardduty (==1.204.0)
Requires-Dist: aws-cdk.aws-healthlake (==1.204.0)
Requires-Dist: aws-cdk.aws-iam (==1.204.0)
Requires-Dist: aws-cdk.aws-identitystore (==1.204.0)
Requires-Dist: aws-cdk.aws-imagebuilder (==1.204.0)
Requires-Dist: aws-cdk.aws-inspector (==1.204.0)
Requires-Dist: aws-cdk.aws-inspectorv2 (==1.204.0)
Requires-Dist: aws-cdk.aws-internetmonitor (==1.204.0)
Requires-Dist: aws-cdk.aws-iot1click (==1.204.0)
Requires-Dist: aws-cdk.aws-iot (==1.204.0)
Requires-Dist: aws-cdk.aws-iotanalytics (==1.204.0)
Requires-Dist: aws-cdk.aws-iotcoredeviceadvisor (==1.204.0)
Requires-Dist: aws-cdk.aws-iotevents (==1.204.0)
Requires-Dist: aws-cdk.aws-iotfleethub (==1.204.0)
Requires-Dist: aws-cdk.aws-iotfleetwise (==1.204.0)
Requires-Dist: aws-cdk.aws-iotsitewise (==1.204.0)
Requires-Dist: aws-cdk.aws-iotthingsgraph (==1.204.0)
Requires-Dist: aws-cdk.aws-iottwinmaker (==1.204.0)
Requires-Dist: aws-cdk.aws-iotwireless (==1.204.0)
Requires-Dist: aws-cdk.aws-ivs (==1.204.0)
Requires-Dist: aws-cdk.aws-ivschat (==1.204.0)
Requires-Dist: aws-cdk.aws-kafkaconnect (==1.204.0)
Requires-Dist: aws-cdk.aws-kendra (==1.204.0)
Requires-Dist: aws-cdk.aws-kendraranking (==1.204.0)
Requires-Dist: aws-cdk.aws-kinesis (==1.204.0)
Requires-Dist: aws-cdk.aws-kinesisanalytics (==1.204.0)
Requires-Dist: aws-cdk.aws-kinesisanalyticsv2 (==1.204.0)
Requires-Dist: aws-cdk.aws-kinesisfirehose (==1.204.0)
Requires-Dist: aws-cdk.aws-kinesisvideo (==1.204.0)
Requires-Dist: aws-cdk.aws-kms (==1.204.0)
Requires-Dist: aws-cdk.aws-lakeformation (==1.204.0)
Requires-Dist: aws-cdk.aws-lambda (==1.204.0)
Requires-Dist: aws-cdk.aws-lex (==1.204.0)
Requires-Dist: aws-cdk.aws-licensemanager (==1.204.0)
Requires-Dist: aws-cdk.aws-lightsail (==1.204.0)
Requires-Dist: aws-cdk.aws-location (==1.204.0)
Requires-Dist: aws-cdk.aws-logs (==1.204.0)
Requires-Dist: aws-cdk.aws-lookoutequipment (==1.204.0)
Requires-Dist: aws-cdk.aws-lookoutmetrics (==1.204.0)
Requires-Dist: aws-cdk.aws-lookoutvision (==1.204.0)
Requires-Dist: aws-cdk.aws-m2 (==1.204.0)
Requires-Dist: aws-cdk.aws-macie (==1.204.0)
Requires-Dist: aws-cdk.aws-managedblockchain (==1.204.0)
Requires-Dist: aws-cdk.aws-mediaconnect (==1.204.0)
Requires-Dist: aws-cdk.aws-mediaconvert (==1.204.0)
Requires-Dist: aws-cdk.aws-medialive (==1.204.0)
Requires-Dist: aws-cdk.aws-mediapackage (==1.204.0)
Requires-Dist: aws-cdk.aws-mediastore (==1.204.0)
Requires-Dist: aws-cdk.aws-mediatailor (==1.204.0)
Requires-Dist: aws-cdk.aws-memorydb (==1.204.0)
Requires-Dist: aws-cdk.aws-msk (==1.204.0)
Requires-Dist: aws-cdk.aws-mwaa (==1.204.0)
Requires-Dist: aws-cdk.aws-neptune (==1.204.0)
Requires-Dist: aws-cdk.aws-networkfirewall (==1.204.0)
Requires-Dist: aws-cdk.aws-networkmanager (==1.204.0)
Requires-Dist: aws-cdk.aws-nimblestudio (==1.204.0)
Requires-Dist: aws-cdk.aws-oam (==1.204.0)
Requires-Dist: aws-cdk.aws-omics (==1.204.0)
Requires-Dist: aws-cdk.aws-opensearchserverless (==1.204.0)
Requires-Dist: aws-cdk.aws-opensearchservice (==1.204.0)
Requires-Dist: aws-cdk.aws-opsworks (==1.204.0)
Requires-Dist: aws-cdk.aws-opsworkscm (==1.204.0)
Requires-Dist: aws-cdk.aws-organizations (==1.204.0)
Requires-Dist: aws-cdk.aws-osis (==1.204.0)
Requires-Dist: aws-cdk.aws-panorama (==1.204.0)
Requires-Dist: aws-cdk.aws-personalize (==1.204.0)
Requires-Dist: aws-cdk.aws-pinpoint (==1.204.0)
Requires-Dist: aws-cdk.aws-pinpointemail (==1.204.0)
Requires-Dist: aws-cdk.aws-pipes (==1.204.0)
Requires-Dist: aws-cdk.aws-proton (==1.204.0)
Requires-Dist: aws-cdk.aws-qldb (==1.204.0)
Requires-Dist: aws-cdk.aws-quicksight (==1.204.0)
Requires-Dist: aws-cdk.aws-ram (==1.204.0)
Requires-Dist: aws-cdk.aws-rds (==1.204.0)
Requires-Dist: aws-cdk.aws-redshift (==1.204.0)
Requires-Dist: aws-cdk.aws-redshiftserverless (==1.204.0)
Requires-Dist: aws-cdk.aws-refactorspaces (==1.204.0)
Requires-Dist: aws-cdk.aws-rekognition (==1.204.0)
Requires-Dist: aws-cdk.aws-resiliencehub (==1.204.0)
Requires-Dist: aws-cdk.aws-resourceexplorer2 (==1.204.0)
Requires-Dist: aws-cdk.aws-resourcegroups (==1.204.0)
Requires-Dist: aws-cdk.aws-robomaker (==1.204.0)
Requires-Dist: aws-cdk.aws-rolesanywhere (==1.204.0)
Requires-Dist: aws-cdk.aws-route53 (==1.204.0)
Requires-Dist: aws-cdk.aws-route53recoverycontrol (==1.204.0)
Requires-Dist: aws-cdk.aws-route53recoveryreadiness (==1.204.0)
Requires-Dist: aws-cdk.aws-route53resolver (==1.204.0)
Requires-Dist: aws-cdk.aws-rum (==1.204.0)
Requires-Dist: aws-cdk.aws-s3 (==1.204.0)
Requires-Dist: aws-cdk.aws-s3objectlambda (==1.204.0)
Requires-Dist: aws-cdk.aws-s3outposts (==1.204.0)
Requires-Dist: aws-cdk.aws-sagemaker (==1.204.0)
Requires-Dist: aws-cdk.aws-sam (==1.204.0)
Requires-Dist: aws-cdk.aws-scheduler (==1.204.0)
Requires-Dist: aws-cdk.aws-sdb (==1.204.0)
Requires-Dist: aws-cdk.aws-secretsmanager (==1.204.0)
Requires-Dist: aws-cdk.aws-securityhub (==1.204.0)
Requires-Dist: aws-cdk.aws-servicecatalog (==1.204.0)
Requires-Dist: aws-cdk.aws-servicecatalogappregistry (==1.204.0)
Requires-Dist: aws-cdk.aws-servicediscovery (==1.204.0)
Requires-Dist: aws-cdk.aws-ses (==1.204.0)
Requires-Dist: aws-cdk.aws-shield (==1.204.0)
Requires-Dist: aws-cdk.aws-signer (==1.204.0)
Requires-Dist: aws-cdk.aws-simspaceweaver (==1.204.0)
Requires-Dist: aws-cdk.aws-sns (==1.204.0)
Requires-Dist: aws-cdk.aws-sqs (==1.204.0)
Requires-Dist: aws-cdk.aws-ssm (==1.204.0)
Requires-Dist: aws-cdk.aws-ssmcontacts (==1.204.0)
Requires-Dist: aws-cdk.aws-ssmincidents (==1.204.0)
Requires-Dist: aws-cdk.aws-sso (==1.204.0)
Requires-Dist: aws-cdk.aws-stepfunctions (==1.204.0)
Requires-Dist: aws-cdk.aws-supportapp (==1.204.0)
Requires-Dist: aws-cdk.aws-synthetics (==1.204.0)
Requires-Dist: aws-cdk.aws-systemsmanagersap (==1.204.0)
Requires-Dist: aws-cdk.aws-timestream (==1.204.0)
Requires-Dist: aws-cdk.aws-transfer (==1.204.0)
Requires-Dist: aws-cdk.aws-voiceid (==1.204.0)
Requires-Dist: aws-cdk.aws-vpclattice (==1.204.0)
Requires-Dist: aws-cdk.aws-waf (==1.204.0)
Requires-Dist: aws-cdk.aws-wafregional (==1.204.0)
Requires-Dist: aws-cdk.aws-wafv2 (==1.204.0)
Requires-Dist: aws-cdk.aws-wisdom (==1.204.0)
Requires-Dist: aws-cdk.aws-workspaces (==1.204.0)
Requires-Dist: aws-cdk.aws-xray (==1.204.0)
Requires-Dist: aws-cdk.core (==1.204.0)
Requires-Dist: constructs (<4.0.0,>=3.3.69)
Requires-Dist: jsii (<2.0.0,>=1.84.0)
Requires-Dist: publication (>=0.0.3)
Requires-Dist: typeguard (~=2.13.3)
